setup.py
adels_dsnd_probability/Binomialdistribution.py
adels_dsnd_probability/Gaussiandistribution.py
adels_dsnd_probability/Generaldistribution.py
adels_dsnd_probability/__init__.py
adels_dsnd_probability.egg-info/PKG-INFO
adels_dsnd_probability.egg-info/SOURCES.txt
adels_dsnd_probability.egg-info/dependency_links.txt
adels_dsnd_probability.egg-info/not-zip-safe
adels_dsnd_probability.egg-info/top_level.txt